{"user": {"id": "3984108068", "screen_name": "冉冉橪", "gender": "m", "birthday": "", "location": "", "education": "", "company": "", "registration_time": "", "sunshine": "", "statuses_count": 963, "followers_count": 445000, "follow_count": 217, "description": "ins：ranranele", "profile_url": "https://m.weibo.cn/u/3984108068?", "profile_image_url": "https://tvax2.sinaimg.cn/crop.0.0.1080.1080.180/ed78aa24ly8hp87bflfpyj20u00u0ta3.jpg?KID=imgbed,tva&Expires=1732900172&ssig=DpVFcjhS6%2F", "avatar_hd": "https://wx2.sinaimg.cn/orj480/ed78aa24ly8hp87bflfpyj20u00u0ta3.jpg", "urank": 37, "mbrank": 6, "verified": false, "verified_type": -1, "verified_reason": ""}, "weibo": [{"user_id": 3984108068, "screen_name": "冉冉橪", "id": 5104718398887587, "bid": "P1YKjBi4b", "text": "上海的阴天☁️ ", "article_url": "", "pics": "https://wx3.sinaimg.cn/large/ed78aa24gy1hvytu2axiyj221d2pve81.jpg,https://wx1.sinaimg.cn/large/ed78aa24gy1hvytu64merj21zp2nl1kx.jpg,https://wx4.sinaimg.cn/large/ed78aa24gy1hvytu4dyvoj22432tge81.jpg,https://wx2.sinaimg.cn/large/ed78aa24gy1hvytu9cyymj21i5202atm.jpg,https://wx4.sinaimg.cn/large/ed78aa24gy1hvytu8lm5pj22c03401ky.jpg,https://wx4.sinaimg.cn/large/ed78aa24gy1hvytug9rx6j22c0340kjl.jpg,https://wx1.sinaimg.cn/large/ed78aa24gy1hvytuf759rj21sg2dshdt.jpg,https://wx1.sinaimg.cn/large/ed78aa24gy1hvytudscovj21sg2ds4qp.jpg,https://wx1.sinaimg.cn/large/ed78aa24gy1hvytuc72qaj225b2v3npd.jpg,https://wx2.sinaimg.cn/large/ed78aa24gy1hvyttz2899j21nn27j4qp.jpg", "video_url": "https://video.weibo.com/media/play?livephoto=https%3A%2F%2Flivephoto.us.sinaimg.cn%2F0036cpQWgx08jS4Rk7aE0f0f0100jCA70k01.mov", "location": "", "created_at": "2024-11-25T21:59:30", "source": "iPhone 16 Pro", "attitudes_count": 640, "comments_count": 41, "reposts_count": 6, "topics": "", "at_users": "", "full_created_at": "2024-11-25 21:59:30"}]}