{"user": {"id": "6251436361", "screen_name": "我是机器Sam_转生版", "gender": "m", "birthday": "", "location": "", "education": "", "company": "", "registration_time": "", "sunshine": "", "statuses_count": 278, "followers_count": 2708, "follow_count": 466, "description": "", "profile_url": "https://m.weibo.cn/u/6251436361?", "profile_image_url": "https://tvax3.sinaimg.cn/crop.0.0.829.829.180/006P4oaJly8gt6uskbxraj30n10n1aax.jpg?KID=imgbed,tva&Expires=1732891231&ssig=xzZM2Xb3ah", "avatar_hd": "https://wx3.sinaimg.cn/orj480/006P4oaJly8gt6uskbxraj30n10n1aax.jpg", "urank": 1, "mbrank": 6, "verified": false, "verified_type": -1, "verified_reason": ""}, "weibo": [{"user_id": 6251436361, "screen_name": "我是机器Sam_转生版", "id": 5103545581833231, "bid": "P1ueG7GUf", "text": "睡醒发现某岛的超S炮倒台了 ", "article_url": "", "pics": "", "video_url": "", "location": "", "created_at": "2024-11-22T16:19:08", "source": "iPhone客户端", "attitudes_count": 0, "comments_count": 3, "reposts_count": 0, "topics": "", "at_users": "", "full_created_at": "2024-11-22 16:19:08"}]}