{"user": {"id": "7525263687", "screen_name": "航天总医院-堵顶云", "gender": "m", "birthday": "", "location": "", "education": "", "company": "", "registration_time": "", "sunshine": "", "statuses_count": 1558, "followers_count": 16000, "follow_count": 78, "description": "脂肪修复 正高级医师", "profile_url": "https://m.weibo.cn/u/7525263687?", "profile_image_url": "https://tvax3.sinaimg.cn/crop.0.0.996.996.180/008dheQLly8glqn8b73jlj30ro0ro40e.jpg?KID=imgbed,tva&Expires=1732882955&ssig=aZHfRNEISM", "avatar_hd": "https://wx3.sinaimg.cn/orj480/008dheQLly8glqn8b73jlj30ro0ro40e.jpg", "urank": 0, "mbrank": 6, "verified": true, "verified_type": 0, "verified_reason": "北京航天总医院 医疗美容科科室主任 堵顶云"}, "weibo": [{"user_id": 7525263687, "screen_name": "航天总医院-堵顶云", "id": 5105803921196361, "bid": "P2qZa51e9", "text": "吸脂\n 【手臂吸脂修复➕肩胛➕后背吸脂➕富贵包吸脂➕斜方肌吸脂➕钻石精雕】术后1个月#堵顶云钻石精雕##堵顶云体雕##北京抽脂##吸脂##上臂吸脂##手臂吸脂# ", "article_url": "", "pics": "https://wx4.sinaimg.cn/large/008dheQLly1hw2ala93p2j312z0u0djh.jpg,https://wx3.sinaimg.cn/large/008dheQLly1hw2alak50yj312x0u077x.jpg,https://wx3.sinaimg.cn/large/008dheQLly1hw2alauuzdj312y0u0q6o.jpg,https://wx3.sinaimg.cn/large/008dheQLly1hw2alb9wr2j312y0u042f.jpg,https://wx4.sinaimg.cn/large/008dheQLly1hw2albhp3uj31330u00wh.jpg,https://wx1.sinaimg.cn/large/008dheQLly1hw2albs7e8j312u0u0juz.jpg,https://wx1.sinaimg.cn/large/008dheQLly1hw2alc3xgsj30u01330wl.jpg,https://wx3.sinaimg.cn/large/008dheQLly1hw2alcd01xj30u012yjuo.jpg,https://wx4.sinaimg.cn/large/008dheQLly1hw2alcmwqrj30u013577t.jpg", "video_url": "", "location": "", "created_at": "2024-11-28T21:52:59", "source": "吸脂超话", "attitudes_count": 0, "comments_count": 0, "reposts_count": 0, "topics": "堵顶云钻石精雕,堵顶云体雕,北京抽脂,吸脂,上臂吸脂,手臂吸脂", "at_users": "", "full_created_at": "2024-11-28 21:52:59"}, {"user_id": 7525263687, "screen_name": "航天总医院-堵顶云", "id": 5105442294599164, "bid": "P2hzTjis4", "text": "吸脂#臀腿一体#术后即刻\n方案：钻石精雕【大小腿吸脂+假胯吸脂】➕填臀➕填胯➕臀线填充➕臀下缘打薄➕香蕉腹打薄\n【吸脂】共计4500ml\n【填充】共计1410ml\n填臀：共930ml，左侧480ml、右侧450ml\n填胯：共360ml，单侧180ml\n臀线填充：共120ml、单侧60ml#堵顶云钻石精雕##堵顶云体雕##北京抽脂##大腿吸脂##大腿环吸##大腿抽脂##小腿吸脂##丰臀##自体脂肪丰臀#", "article_url": "", "pics": "https://wx3.sinaimg.cn/large/008dheQLly1hw151s7snmj30u00u3q6k.jpg,https://wx3.sinaimg.cn/large/008dheQLly1hw151sf6quj30u012z43z.jpg,https://wx3.sinaimg.cn/large/008dheQLly1hw151slbf0j30u50u0adj.jpg,https://wx2.sinaimg.cn/large/008dheQLly1hw151srm0dj30u0131wk6.jpg,https://wx1.sinaimg.cn/large/008dheQLly1hw151r8idzj31hc0u0jte.jpg,https://wx1.sinaimg.cn/large/008dheQLly1hw151qo9ukj31hc0u0gnr.jpg,https://wx1.sinaimg.cn/large/008dheQLly1hw151zaw6pj31hc0u040d.jpg,https://wx2.sinaimg.cn/large/008dheQLly1hw151xet7xj31hc0u040k.jpg,https://wx1.sinaimg.cn/large/008dheQLly1hw151zfkeoj31hc0u0taf.jpg", "video_url": "https://f.video.weibocdn.com/o0/yvGP8qzulx08jVgnvyUw010412006i4F0E010.mp4?label=mp4_720p&template=1280x720.25.0&ori=0&ps=1BThihd3VLAY5R&Expires=1732875757&ssig=dh70bzN%2FJh&KID=unistore,video", "location": "", "created_at": "2024-11-27T21:56:00", "source": "吸脂超话", "attitudes_count": 8, "comments_count": 1, "reposts_count": 0, "topics": "臀腿一体,堵顶云钻石精雕,堵顶云体雕,北京抽脂,大腿吸脂,大腿环吸,大腿抽脂,小腿吸脂,丰臀,自体脂肪丰臀", "at_users": "", "full_created_at": "2024-11-27 21:56:00"}, {"user_id": 7525263687, "screen_name": "航天总医院-堵顶云", "id": 5105069853509741, "bid": "P27TbeJ2J", "text": "吸脂\n 【腰臀一体】术后8个月\n【手臂吸脂+后背吸脂+自体脂肪丰胸】术后6个月+#堵顶云钻石精雕##堵顶云体雕##自体脂肪丰臀##北京抽脂##吸脂##自体脂肪填充##腰腹吸脂##腰腹环吸##丰臀##隆胸##脂肪隆胸##手臂吸脂# ", "article_url": "", "pics": "https://wx2.sinaimg.cn/large/008dheQLly1hvzya5oodnj30km11it9z.jpg,https://wx3.sinaimg.cn/large/008dheQLly1hvzya1q1wqj30u01h5n19.jpg,https://wx3.sinaimg.cn/large/008dheQLly1hvzya20nxqj30u01hwwiy.jpg,https://wx1.sinaimg.cn/large/008dheQLly1hvzya27lpyj30u01i5tdb.jpg,https://wx4.sinaimg.cn/large/008dheQLly1hvzya2g1iyj30u01i0tcy.jpg,https://wx2.sinaimg.cn/large/008dheQLly1hvzya2qmztj30u01ic42r.jpg,https://wx3.sinaimg.cn/large/008dheQLly1hvzya30wpgj30u00whwhz.jpg,https://wx4.sinaimg.cn/large/008dheQLly1hvzya39g5yj30u012z439.jpg,https://wx4.sinaimg.cn/large/008dheQLly1hvzya3g3irj30u00w7jvl.jpg", "video_url": "https://f.video.weibocdn.com/o0/SMBKjtbvlx08jTCLrjwc0104120036Xp0E010.mp4?label=mp4_720p&template=720x1308.24.0&ori=0&ps=1CwnkDw1GXwCQx&Expires=1732875756&ssig=YVw08LF38E&KID=unistore,video", "location": "", "created_at": "2024-11-26T21:16:03", "source": "吸脂超话", "attitudes_count": 14, "comments_count": 0, "reposts_count": 0, "topics": "堵顶云钻石精雕,堵顶云体雕,自体脂肪丰臀,北京抽脂,吸脂,自体脂肪填充,腰腹吸脂,腰腹环吸,丰臀,隆胸,脂肪隆胸,手臂吸脂", "at_users": "", "full_created_at": "2024-11-26 21:16:03"}, {"user_id": 7525263687, "screen_name": "航天总医院-堵顶云", "id": 5104726351287776, "bid": "P1YX95p0A", "text": "吸脂#自体脂肪丰胸#术后3天#隆胸##脂肪隆胸# ", "article_url": "", "pics": "https://wx4.sinaimg.cn/large/008dheQLly1hvyutrugnwj30u01400tw.jpg,https://wx1.sinaimg.cn/large/008dheQLly1hvyutv2mydj312q0n00tk.jpg,https://wx4.sinaimg.cn/large/008dheQLly1hvyutxym1cj313y0q0jsd.jpg,https://wx1.sinaimg.cn/large/008dheQLly1hvyuu1gstuj313y0o2dgp.jpg,https://wx2.sinaimg.cn/large/008dheQLly1hvyutsixuej30u014043o.jpg,https://wx2.sinaimg.cn/large/008dheQLly1hvyutss9imj30u0140tdl.jpg", "video_url": "https://f.video.weibocdn.com/o0/zukpTVELlx08jS713uM8010412001cwS0E010.mp4?label=mp4_720p&template=720x960.24.0&ori=0&ps=1CwnkDw1GXwCQx&Expires=1732875756&ssig=yqWV%2B%2BTjlq&KID=unistore,video", "location": "", "created_at": "2024-11-25T22:31:06", "source": "吸脂超话", "attitudes_count": 14, "comments_count": 0, "reposts_count": 0, "topics": "自体脂肪丰胸,隆胸,脂肪隆胸", "at_users": "", "full_created_at": "2024-11-25 22:31:06"}, {"user_id": 7525263687, "screen_name": "航天总医院-堵顶云", "id": 5104347606680299, "bid": "P1P6gs1QL", "text": "丰胸隆胸#自体脂肪填充#术后即刻\n填充共计：700ml，单侧350ml#隆胸##脂肪隆胸# ", "article_url": "", "pics": "https://wx2.sinaimg.cn/large/008dheQLly1hvxnbqt1w2j30u0140dhi.jpg,https://wx2.sinaimg.cn/large/008dheQLly1hvxnbwa6c5j31g20r0wfr.jpg,https://wx3.sinaimg.cn/large/008dheQLly1hvxnbvtuucj31hc0simyb.jpg,https://wx3.sinaimg.cn/large/008dheQLly1hvxnbwyk1tj313y0poab6.jpg", "video_url": "https://f.video.weibocdn.com/o0/T9z2eyi2lx08jQrEq8TC0104120015XX0E010.mp4?label=mp4_720p&template=720x960.24.0&ori=0&ps=1CwnkDw1GXwCQx&Expires=1732875756&ssig=N%2BvaZ%2Fatok&KID=unistore,video", "location": "", "created_at": "2024-11-24T21:26:05", "source": "丰胸隆胸超话", "attitudes_count": 4, "comments_count": 0, "reposts_count": 0, "topics": "自体脂肪填充,隆胸,脂肪隆胸", "at_users": "", "full_created_at": "2024-11-24 21:26:05"}, {"user_id": 7525263687, "screen_name": "航天总医院-堵顶云", "id": 5104340838915324, "bid": "P1OVlBphy", "text": "丰胸隆胸#自体脂肪填充#术后即刻\n填充共计：700ml，单侧350ml#隆胸##脂肪隆胸# ", "article_url": "", "pics": "https://wx3.sinaimg.cn/large/008dheQLly1hvxmjq9qkyj30u0140dhi.jpg,https://wx4.sinaimg.cn/large/008dheQLly1hvxmjzsuxhj31g20r0wfr.jpg,https://wx2.sinaimg.cn/large/008dheQLly1hvxmjxzjvoj31hc0simyb.jpg", "video_url": "https://f.video.weibocdn.com/o0/a9W3CUYAlx08jQpNXBbi0104120015XX0E010.mp4?label=mp4_720p&template=720x960.24.0&ori=0&ps=1CwnkDw1GXwCQx&Expires=1732875756&ssig=IyXWFr2TqD&KID=unistore,video", "location": "", "created_at": "2024-11-24T20:59:13", "source": "丰胸隆胸超话", "attitudes_count": 4, "comments_count": 0, "reposts_count": 1, "topics": "自体脂肪填充,隆胸,脂肪隆胸", "at_users": "", "full_created_at": "2024-11-24 20:59:13"}, {"user_id": 7525263687, "screen_name": "航天总医院-堵顶云", "id": 5103987594627844, "bid": "P1FJBjpUE", "text": "吸脂#手臂吸脂#修复术后即刻\n吸脂共计：800ml，单侧各400ml#堵顶云钻石精雕##堵顶云体雕##北京抽脂##吸脂##上臂吸脂##手臂吸脂# ", "article_url": "", "pics": "https://wx3.sinaimg.cn/large/008dheQLly1hvwhzm89c8j30u0130n2e.jpg,https://wx3.sinaimg.cn/large/008dheQLly1hvwhzmj1f4j30u012zgre.jpg", "video_url": "", "location": "", "created_at": "2024-11-23T21:35:33", "source": "吸脂超话", "attitudes_count": 2, "comments_count": 1, "reposts_count": 0, "topics": "手臂吸脂,堵顶云钻石精雕,堵顶云体雕,北京抽脂,吸脂,上臂吸脂,手臂吸脂", "at_users": "", "full_created_at": "2024-11-23 21:35:33"}, {"user_id": 7525263687, "screen_name": "航天总医院-堵顶云", "id": 5103845558715122, "bid": "P1C2vAzcu", "text": "#臀腿一体#术后4个月\n方案：大小腿凹凸修复➕钻石精雕➕臀线修复➕填臀胯#堵顶云钻石精雕##堵顶云体雕##北京抽脂##大腿吸脂##大腿环吸##大腿抽脂##小腿吸脂##丰臀##自体脂肪丰臀#吸脂\n ", "article_url": "", "pics": "https://wx3.sinaimg.cn/large/008dheQLly1hvw1krkhtfj30u00y6tap.jpg,https://wx2.sinaimg.cn/large/008dheQLly1hvw1lapwzij30u00y6jt9.jpg,https://wx1.sinaimg.cn/large/008dheQLly1hvw1mki8ojj30u00y640e.jpg,https://wx3.sinaimg.cn/large/008dheQLly1hvw1n6rug6j30u00y6abz.jpg,https://wx2.sinaimg.cn/large/008dheQLly1hvw1ntg5n5j30u00y6gng.jpg,https://wx2.sinaimg.cn/large/008dheQLly1hvw1obxgdxj30u00y60ul.jpg,https://wx1.sinaimg.cn/large/008dheQLly1hvw1j51ak1j31hc1xu1kx.jpg,https://wx1.sinaimg.cn/large/008dheQLly1hvw1j9fal7j31hc1zcqu1.jpg,https://wx3.sinaimg.cn/large/008dheQLly1hvw1jb8w0ej31q41c17na.jpg", "video_url": "https://f.video.weibocdn.com/o0/LvFjc13Blx08jOerDHD2010412005IdV0E010.mp4?label=mp4_720p&template=720x820.24.0&ori=0&ps=1CwnkDw1GXwCQx&Expires=1732875756&ssig=NhC8Ol29ip&KID=unistore,video", "location": "", "created_at": "2024-11-23T12:11:09", "source": "吸脂超话", "attitudes_count": 27, "comments_count": 1, "reposts_count": 0, "topics": "臀腿一体,堵顶云钻石精雕,堵顶云体雕,北京抽脂,大腿吸脂,大腿环吸,大腿抽脂,小腿吸脂,丰臀,自体脂肪丰臀", "at_users": "", "full_created_at": "2024-11-23 12:11:09"}, {"user_id": 7525263687, "screen_name": "航天总医院-堵顶云", "id": 5103724797886681, "bid": "P1yTJx5Gx", "text": "#臀腿一体#术后4个月\n方案：大小腿凹凸修复➕钻石精雕➕臀线修复➕填臀胯#堵顶云钻石精雕##堵顶云体雕##北京抽脂##大腿吸脂##大腿环吸##大腿抽脂##小腿吸脂##丰臀##自体脂肪丰臀# ", "article_url": "", "pics": "https://wx3.sinaimg.cn/large/008dheQLly1hvvnmejg8kj30u00y6ac1.jpg,https://wx4.sinaimg.cn/large/008dheQLly1hvvnn425lzj30u00y6gnk.jpg,https://wx3.sinaimg.cn/large/008dheQLly1hvvnnrfb2dj30u00y6gni.jpg,https://wx1.sinaimg.cn/large/008dheQLly1hvvnoczemzj30u00y6wgc.jpg,https://wx3.sinaimg.cn/large/008dheQLly1hvvnp9dhgcj30u00y6mz0.jpg,https://wx3.sinaimg.cn/large/008dheQLly1hvvnr1qlb5j30u00y6wgc.jpg,https://wx2.sinaimg.cn/large/008dheQLly1hvvnjpltblj31hc1xu1kx.jpg,https://wx4.sinaimg.cn/large/008dheQLly1hvvnjty8grj31hc1zcqu1.jpg,https://wx1.sinaimg.cn/large/008dheQLly1hvvnjvmdxqj31q41c17na.jpg", "video_url": "https://f.video.weibocdn.com/o0/cWWbMLqalx08jNHhAYmY010412005ObE0E010.mp4?label=mp4_720p&template=720x820.24.0&ori=0&ps=1CwnkDw1GXwCQx&Expires=1732875756&ssig=2SmfHd4VVh&KID=unistore,video", "location": "", "created_at": "2024-11-23T04:11:17", "source": "吸脂超话", "attitudes_count": 4, "comments_count": 0, "reposts_count": 0, "topics": "臀腿一体,堵顶云钻石精雕,堵顶云体雕,北京抽脂,大腿吸脂,大腿环吸,大腿抽脂,小腿吸脂,丰臀,自体脂肪丰臀", "at_users": "", "full_created_at": "2024-11-23 04:11:17"}, {"user_id": 7525263687, "screen_name": "航天总医院-堵顶云", "id": 5103259270514173, "bid": "P1mMT29L7", "text": "吸脂#小腿吸脂#术后即刻#堵顶云钻石精雕##堵顶云体雕##北京抽脂##小腿吸脂##瘦小腿# ", "article_url": "", "pics": "https://wx1.sinaimg.cn/large/008dheQLly1hvu6cdejrkj312t0u0n1z.jpg,https://wx2.sinaimg.cn/large/008dheQLly1hvu6cdnl57j31310u0798.jpg,https://wx3.sinaimg.cn/large/008dheQLly1hvu6cdx2pmj312v0u0dk3.jpg", "video_url": "", "location": "", "created_at": "2024-11-21T21:21:27", "source": "吸脂超话", "attitudes_count": 1, "comments_count": 0, "reposts_count": 0, "topics": "小腿吸脂,堵顶云钻石精雕,堵顶云体雕,北京抽脂,小腿吸脂,瘦小腿", "at_users": "", "full_created_at": "2024-11-21 21:21:27"}, {"user_id": 7525263687, "screen_name": "航天总医院-堵顶云", "id": 5102902546269702, "bid": "P1dvwqj2e", "text": "丰胸隆胸#自体脂肪丰胸#术后3天#隆胸##脂肪隆胸# \n航天总医院-堵顶云的微博视频\n ", "article_url": "", "pics": "", "video_url": "https://f.video.weibocdn.com/o0/lgW7OwmOlx08jK5kTP6E010412002nTK0E010.mp4?label=mp4_720p&template=720x960.24.0&ori=0&ps=1CwnkDw1GXwCQx&Expires=1732875757&ssig=%2BZb%2BFd2Krn&KID=unistore,video", "location": "", "created_at": "2024-11-20T21:43:57", "source": "丰胸隆胸超话", "attitudes_count": 39, "comments_count": 1, "reposts_count": 3, "topics": "自体脂肪丰胸,隆胸,脂肪隆胸", "at_users": "", "full_created_at": "2024-11-20 21:43:57"}, {"user_id": 7525263687, "screen_name": "航天总医院-堵顶云", "id": 5102538363503087, "bid": "P1428eHjp", "text": "吸脂\n 钻石精雕【小腿+膝盖+假胯】吸脂➕填臀#堵顶云钻石精雕##堵顶云体雕##北京抽脂##小腿吸脂##丰臀##自体脂肪丰臀# ", "article_url": "", "pics": "https://wx3.sinaimg.cn/large/008dheQLly1hvrvi2slqjj31hc0u0zm8.jpg,https://wx3.sinaimg.cn/large/008dheQLly1hvrvi7j930j31hc0u076d.jpg,https://wx1.sinaimg.cn/large/008dheQLly1hvrviebm1mj31hc0u040g.jpg,https://wx2.sinaimg.cn/large/008dheQLly1hvrvipvoxcj31hc0u0jtv.jpg,https://wx1.sinaimg.cn/large/008dheQLly1hvrviwft0ej31400u0gmv.jpg,https://wx4.sinaimg.cn/large/008dheQLly1hvrvj7ipblj31400u0wg7.jpg,https://wx3.sinaimg.cn/large/008dheQLly1hvrvjbly9cj31400u0q4o.jpg,https://wx2.sinaimg.cn/large/008dheQLly1hvrvjewjh7j31hc0u0gno.jpg,https://wx1.sinaimg.cn/large/008dheQLly1hvrvj8xhxmj30wi0nymzl.jpg", "video_url": "https://f.video.weibocdn.com/o0/cXsbeCeslx08jItRjMp2010412005DWq0E010.mp4?label=mp4_720p&template=1280x720.25.0&ori=0&ps=1CwnkDw1GXwCQx&Expires=1732875757&ssig=At8ZfkfJOY&KID=unistore,video", "location": "", "created_at": "2024-11-19T21:36:48", "source": "吸脂超话", "attitudes_count": 12, "comments_count": 1, "reposts_count": 1, "topics": "堵顶云钻石精雕,堵顶云体雕,北京抽脂,小腿吸脂,丰臀,自体脂肪丰臀", "at_users": "", "full_created_at": "2024-11-19 21:36:48"}]}