{"user": {"id": "1075732170", "screen_name": "天津牙医吕春阳", "gender": "m", "birthday": "", "location": "", "education": "", "company": "", "registration_time": "", "sunshine": "", "statuses_count": 24880, "followers_count": 152000, "follow_count": 803, "description": "天津牙体牙髓病专委会委员，第四届登士柏全国根管治疗10强赛 非口腔专科医院组二等奖 擅长根管治疗 树脂修复 前牙美学修复", "profile_url": "https://m.weibo.cn/u/1075732170?", "profile_image_url": "https://tvax1.sinaimg.cn/crop.0.0.512.512.180/401e5ecaly8gdil84gla5j20e80e8wex.jpg?KID=imgbed,tva&Expires=1732886466&ssig=awQdTB7nF0", "avatar_hd": "https://wx1.sinaimg.cn/orj480/401e5ecaly8gdil84gla5j20e80e8wex.jpg", "urank": 47, "mbrank": 6, "verified": false, "verified_type": -1, "verified_reason": ""}, "weibo": [{"user_id": 1075732170, "screen_name": "天津牙医吕春阳", "id": 5105928900968673, "bid": "P2ueK43ZL", "text": "学习了\n，国老辛苦", "article_url": "", "pics": "", "video_url": "", "location": "", "created_at": "2024-11-29T06:09:36", "source": "iPhone 13 Pro", "attitudes_count": 7, "comments_count": 0, "reposts_count": 2, "topics": "", "at_users": "", "retweet": {"user_id": 1336435857, "screen_name": "济南牙医国洪波", "id": 5105460151847935, "bid": "P2i2H7KJp", "text": "发布了头条文章：《磷酸酸蚀 - 多长是太长、多短是太短、过度酸蚀或酸蚀不足有什么危害》  \n磷酸酸蚀 - 多长是太长、多短是太短、过度酸蚀或酸蚀不足有什么危害\n ", "article_url": "", "pics": "", "video_url": "", "location": "", "created_at": "2024-11-27T23:06:58", "source": "微博 weibo.com", "attitudes_count": 217, "comments_count": 22, "reposts_count": 137, "topics": "", "at_users": "", "full_created_at": "2024-11-27 23:06:58"}, "full_created_at": "2024-11-29 06:09:36"}, {"user_id": 1075732170, "screen_name": "天津牙医吕春阳", "id": 5105648587508076, "bid": "P2mWCvvc0", "text": "这是事实\n//@牙医小小徐:昨天问一个上海牙医，“为什么杭州成了牙科培训的热门城市而不是上海？” 回答：上海贵", "article_url": "", "pics": "", "video_url": "", "location": "", "created_at": "2024-11-28T11:35:44", "source": "iPhone 13 Pro", "attitudes_count": 1, "comments_count": 0, "reposts_count": 0, "topics": "", "at_users": "牙医小小徐", "retweet": {"user_id": 1075732170, "screen_name": "天津牙医吕春阳", "id": 5105224555693058, "bid": "P2bUHnT1w", "text": "今年最后一次3天的课程，能够把我自己对微创的理念包括直接间接的理解表达清楚的课程，估计明年大概率不会有三天的课程了，年纪大了3天有点顶不住了[破涕为笑]，地点杭州，主办方牙朮[抱拳][抱拳][抱拳] ", "article_url": "", "pics": "https://wx4.sinaimg.cn/large/401e5ecaly1hw0g1pdrttj20u03br7po.jpg", "video_url": "", "location": "", "created_at": "2024-11-27T07:30:47", "source": "iPhone 13 Pro", "attitudes_count": 12, "comments_count": 14, "reposts_count": 13, "topics": "", "at_users": "", "full_created_at": "2024-11-27 07:30:47"}, "full_created_at": "2024-11-28 11:35:44"}, {"user_id": 1075732170, "screen_name": "天津牙医吕春阳", "id": 5105403517734228, "bid": "P2gzlws1C", "text": "回复@山西新绛健齿口腔-郝小军:谢谢\n//@山西新绛健齿口腔-郝小军:", "article_url": "", "pics": "", "video_url": "", "location": "", "created_at": "2024-11-27T19:21:55", "source": "iPhone 13 Pro", "attitudes_count": 0, "comments_count": 0, "reposts_count": 0, "topics": "", "at_users": "山西新绛健齿口腔-郝小军,山西新绛健齿口腔-郝小军", "retweet": {"user_id": 1075732170, "screen_name": "天津牙医吕春阳", "id": 5105224555693058, "bid": "P2bUHnT1w", "text": "今年最后一次3天的课程，能够把我自己对微创的理念包括直接间接的理解表达清楚的课程，估计明年大概率不会有三天的课程了，年纪大了3天有点顶不住了[破涕为笑]，地点杭州，主办方牙朮[抱拳][抱拳][抱拳] ", "article_url": "", "pics": "https://wx4.sinaimg.cn/large/401e5ecaly1hw0g1pdrttj20u03br7po.jpg", "video_url": "", "location": "", "created_at": "2024-11-27T07:30:47", "source": "iPhone 13 Pro", "attitudes_count": 12, "comments_count": 14, "reposts_count": 13, "topics": "", "at_users": "", "full_created_at": "2024-11-27 07:30:47"}, "full_created_at": "2024-11-27 19:21:55"}, {"user_id": 1075732170, "screen_name": "天津牙医吕春阳", "id": 5105403463991870, "bid": "P2gzggKt0", "text": "回复@小刘已打烊:不想绝版，但是有时候没办法，随缘吧\n//@小刘已打烊:吕老师不能绝版啊", "article_url": "", "pics": "", "video_url": "", "location": "", "created_at": "2024-11-27T19:21:41", "source": "iPhone 13 Pro", "attitudes_count": 1, "comments_count": 0, "reposts_count": 0, "topics": "", "at_users": "小刘已打烊,小刘已打烊", "retweet": {"user_id": 1075732170, "screen_name": "天津牙医吕春阳", "id": 5105224555693058, "bid": "P2bUHnT1w", "text": "今年最后一次3天的课程，能够把我自己对微创的理念包括直接间接的理解表达清楚的课程，估计明年大概率不会有三天的课程了，年纪大了3天有点顶不住了[破涕为笑]，地点杭州，主办方牙朮[抱拳][抱拳][抱拳] ", "article_url": "", "pics": "https://wx4.sinaimg.cn/large/401e5ecaly1hw0g1pdrttj20u03br7po.jpg", "video_url": "", "location": "", "created_at": "2024-11-27T07:30:47", "source": "iPhone 13 Pro", "attitudes_count": 12, "comments_count": 14, "reposts_count": 13, "topics": "", "at_users": "", "full_created_at": "2024-11-27 07:30:47"}, "full_created_at": "2024-11-27 19:21:41"}, {"user_id": 1075732170, "screen_name": "天津牙医吕春阳", "id": 5105403233568140, "bid": "P2gyTeYeE", "text": "回复@许桐楷:谢谢许老师\n//@许桐楷:\n绝版三天课程", "article_url": "", "pics": "", "video_url": "", "location": "", "created_at": "2024-11-27T19:20:47", "source": "iPhone 13 Pro", "attitudes_count": 0, "comments_count": 0, "reposts_count": 0, "topics": "", "at_users": "许桐楷,许桐楷", "retweet": {"user_id": 1075732170, "screen_name": "天津牙医吕春阳", "id": 5105224555693058, "bid": "P2bUHnT1w", "text": "今年最后一次3天的课程，能够把我自己对微创的理念包括直接间接的理解表达清楚的课程，估计明年大概率不会有三天的课程了，年纪大了3天有点顶不住了[破涕为笑]，地点杭州，主办方牙朮[抱拳][抱拳][抱拳] ", "article_url": "", "pics": "https://wx4.sinaimg.cn/large/401e5ecaly1hw0g1pdrttj20u03br7po.jpg", "video_url": "", "location": "", "created_at": "2024-11-27T07:30:47", "source": "iPhone 13 Pro", "attitudes_count": 12, "comments_count": 14, "reposts_count": 13, "topics": "", "at_users": "", "full_created_at": "2024-11-27 07:30:47"}, "full_created_at": "2024-11-27 19:20:47"}, {"user_id": 1075732170, "screen_name": "天津牙医吕春阳", "id": 5105299459675936, "bid": "P2dRvEB9u", "text": "回复@牙医赖俊强:下个月见哈\n//@牙医赖俊强:吕老师，报了您12月的深圳美学树脂课，期待老师的干货输出", "article_url": "", "pics": "", "video_url": "", "location": "", "created_at": "2024-11-27T12:28:26", "source": "iPhone 13 Pro", "attitudes_count": 0, "comments_count": 0, "reposts_count": 0, "topics": "", "at_users": "牙医赖俊强,牙医赖俊强", "retweet": {"user_id": 1075732170, "screen_name": "天津牙医吕春阳", "id": 5105224555693058, "bid": "P2bUHnT1w", "text": "今年最后一次3天的课程，能够把我自己对微创的理念包括直接间接的理解表达清楚的课程，估计明年大概率不会有三天的课程了，年纪大了3天有点顶不住了[破涕为笑]，地点杭州，主办方牙朮[抱拳][抱拳][抱拳] ", "article_url": "", "pics": "https://wx4.sinaimg.cn/large/401e5ecaly1hw0g1pdrttj20u03br7po.jpg", "video_url": "", "location": "", "created_at": "2024-11-27T07:30:47", "source": "iPhone 13 Pro", "attitudes_count": 12, "comments_count": 14, "reposts_count": 13, "topics": "", "at_users": "", "full_created_at": "2024-11-27 07:30:47"}, "full_created_at": "2024-11-27 12:28:26"}, {"user_id": 1075732170, "screen_name": "天津牙医吕春阳", "id": 5105294294910481, "bid": "P2dJbkBrj", "text": "//@根管达人:像是七老八十了", "article_url": "", "pics": "", "video_url": "", "location": "", "created_at": "2024-11-27T12:07:54", "source": "iPhone 13 Pro", "attitudes_count": 0, "comments_count": 0, "reposts_count": 0, "topics": "", "at_users": "根管达人", "retweet": {"user_id": 1075732170, "screen_name": "天津牙医吕春阳", "id": 5105224555693058, "bid": "P2bUHnT1w", "text": "今年最后一次3天的课程，能够把我自己对微创的理念包括直接间接的理解表达清楚的课程，估计明年大概率不会有三天的课程了，年纪大了3天有点顶不住了[破涕为笑]，地点杭州，主办方牙朮[抱拳][抱拳][抱拳] ", "article_url": "", "pics": "https://wx4.sinaimg.cn/large/401e5ecaly1hw0g1pdrttj20u03br7po.jpg", "video_url": "", "location": "", "created_at": "2024-11-27T07:30:47", "source": "iPhone 13 Pro", "attitudes_count": 12, "comments_count": 14, "reposts_count": 13, "topics": "", "at_users": "", "full_created_at": "2024-11-27 07:30:47"}, "full_created_at": "2024-11-27 12:07:54"}, {"user_id": 1075732170, "screen_name": "天津牙医吕春阳", "id": 5105230614365643, "bid": "P2c4tijHB", "text": "回复@草根诗人:哈哈，就服你\n//@草根诗人:三天课程虽短暂，微创理念永流传。", "article_url": "", "pics": "", "video_url": "", "location": "", "created_at": "2024-11-27T07:54:52", "source": "iPhone 13 Pro", "attitudes_count": 1, "comments_count": 0, "reposts_count": 0, "topics": "", "at_users": "草根诗人,草根诗人", "retweet": {"user_id": 1075732170, "screen_name": "天津牙医吕春阳", "id": 5105224555693058, "bid": "P2bUHnT1w", "text": "今年最后一次3天的课程，能够把我自己对微创的理念包括直接间接的理解表达清楚的课程，估计明年大概率不会有三天的课程了，年纪大了3天有点顶不住了[破涕为笑]，地点杭州，主办方牙朮[抱拳][抱拳][抱拳] ", "article_url": "", "pics": "https://wx4.sinaimg.cn/large/401e5ecaly1hw0g1pdrttj20u03br7po.jpg", "video_url": "", "location": "", "created_at": "2024-11-27T07:30:47", "source": "iPhone 13 Pro", "attitudes_count": 12, "comments_count": 14, "reposts_count": 13, "topics": "", "at_users": "", "full_created_at": "2024-11-27 07:30:47"}, "full_created_at": "2024-11-27 07:54:52"}, {"user_id": 1075732170, "screen_name": "天津牙医吕春阳", "id": 5105224555693058, "bid": "P2bUHnT1w", "text": "今年最后一次3天的课程，能够把我自己对微创的理念包括直接间接的理解表达清楚的课程，估计明年大概率不会有三天的课程了，年纪大了3天有点顶不住了[破涕为笑]，地点杭州，主办方牙朮[抱拳][抱拳][抱拳] ", "article_url": "", "pics": "https://wx4.sinaimg.cn/large/401e5ecaly1hw0g1pdrttj20u03br7po.jpg", "video_url": "", "location": "", "created_at": "2024-11-27T07:30:47", "source": "iPhone 13 Pro", "attitudes_count": 12, "comments_count": 14, "reposts_count": 13, "topics": "", "at_users": "", "full_created_at": "2024-11-27 07:30:47"}, {"user_id": 1075732170, "screen_name": "天津牙医吕春阳", "id": 5104210473911364, "bid": "P1Lx5gpww", "text": "道邦真不错，临床需要什么就生产什么套装，这又出了活髓切段套装和取分离器械套装[强][强] ", "article_url": "", "pics": "https://wx4.sinaimg.cn/large/401e5ecaly1hvx7kxde2qj21k80sjajl.jpg,https://wx1.sinaimg.cn/large/401e5ecaly1hvx7kxq3hdj22f31d5awf.jpg,https://wx1.sinaimg.cn/large/401e5ecaly1hvx7kygut1j22c0340e81.jpg,https://wx4.sinaimg.cn/large/401e5ecaly1hvx7kz8zonj22c0340e81.jpg,https://wx3.sinaimg.cn/large/401e5ecaly1hvx7l03vpmj22c0340e81.jpg,https://wx4.sinaimg.cn/large/401e5ecaly1hvx7l0z26sj22c0340kjl.jpg", "video_url": "https://video.weibo.com/media/play?livephoto=https%3A%2F%2Flivephoto.us.sinaimg.cn%2F000gw3GSjx08jPQfhpfO0f0f0100lwSz0k01.mov;https://video.weibo.com/media/play?livephoto=https%3A%2F%2Flivephoto.us.sinaimg.cn%2F002yt2x4jx08jPQfpuAU0f0f0100kKda0k01.mov;https://video.weibo.com/media/play?livephoto=https%3A%2F%2Flivephoto.us.sinaimg.cn%2F002SlMR0jx08jPQfydtB0f0f0100rvK40k01.mov;https://video.weibo.com/media/play?livephoto=https%3A%2F%2Flivephoto.us.sinaimg.cn%2F004ecrRAjx08jPQfHl4A0f0f0100mgJS0k01.mov", "location": "", "created_at": "2024-11-24T12:21:11", "source": "iPhone 13 Pro", "attitudes_count": 59, "comments_count": 2, "reposts_count": 4, "topics": "", "at_users": "", "full_created_at": "2024-11-24 12:21:11"}, {"user_id": 1075732170, "screen_name": "天津牙医吕春阳", "id": 5103146660269735, "bid": "P1jRg18az", "text": "", "article_url": "", "pics": "", "video_url": "", "location": "", "created_at": "2024-11-21T13:53:58", "source": "iPhone 13 Pro", "attitudes_count": 0, "comments_count": 2, "reposts_count": 0, "topics": "", "at_users": "", "retweet": {"user_id": 2698975692, "screen_name": "渊ZP", "id": 5102829677053128, "bid": "P1bBZtAQ8", "text": "#这是一条抽奖微博#总要有第一次\n，抽奖送12本新书中文版《口腔修复和重建中的功能𬌗学》\n关注转发即可\n截止时间：11月22日22点@牙医DrZhou @牙医编辑 @同济大学口腔医院刘伟才 @北京牙医苏建宏 @牙医小小徐 @老毛板 @天津牙医吕春阳 @西安牙医亓 @正畸牙齿德泓万敏 @巴掌大_若只如初见 @北京牙医_胡璐璐 @东田阿姨 @Dory_Du @儿童牙医丁香梧桐 @甘宁Ganning @光华老蒋 @浩华牙医超人 @黄懽DrHUANG @厦门牙医陈国洋 @天津牙医吕春阳 @显微牙医 @牙齿美容微笑设计师黎曙光 @亚明牛仔 @牙医刘宇 @牙医思无邪 @牙医张林-遵义铂菲口腔 @牙周-宝盖丁 @重医口腔种植科白石 @周薇娜医生 @坐堂牙医孙鹏 \n抽奖详情", "article_url": "", "pics": "https://wx2.sinaimg.cn/large/a0df19ccly1hvst07157fj21400u0qbu.jpg,https://wx3.sinaimg.cn/large/a0df19ccly1hvst07doqyj20u0140dkx.jpg,https://wx4.sinaimg.cn/large/a0df19ccly1hvst03agwrj20xm0u0afj.jpg", "video_url": "", "location": "", "created_at": "2024-11-20T16:54:23", "source": "微博轻享版", "attitudes_count": 58, "comments_count": 142, "reposts_count": 420, "topics": "这是一条抽奖微博", "at_users": "牙医DrZhou,牙医编辑,同济大学口腔医院刘伟才,北京牙医苏建宏,牙医小小徐,老毛板,天津牙医吕春阳,西安牙医亓,正畸牙齿德泓万敏,巴掌大_若只如初见,北京牙医_胡璐璐,东田阿姨,Dory_Du,儿童牙医丁香梧桐,甘宁Ganning,光华老蒋,浩华牙医超人,黄懽DrHUANG,厦门牙医陈国洋,天津牙医吕春阳,显微牙医,牙齿美容微笑设计师黎曙光,亚明牛仔,牙医刘宇,牙医思无邪,牙医张林-遵义铂菲口腔,牙周-宝盖丁,重医口腔种植科白石,周薇娜医生,坐堂牙医孙鹏", "full_created_at": "2024-11-20 16:54:23"}, "full_created_at": "2024-11-21 13:53:58"}]}