{"user": {"id": "6264137579", "screen_name": "Coldnessinmyheart2", "gender": "m", "birthday": "", "location": "", "education": "", "company": "", "registration_time": "", "sunshine": "", "statuses_count": 1764, "followers_count": 9526, "follow_count": 309, "description": "一定要堕落下去 直到和我一样 。重度药物滥用。", "profile_url": "https://m.weibo.cn/u/6264137579?", "profile_image_url": "https://tvax1.sinaimg.cn/default/images/default_avatar_male_180.gif?KID=imgbed,tva&Expires=1732898554&ssig=J%2BAREBz7pQ", "avatar_hd": "https://ss1.sinaimg.cn/orj480/default_avatar_male_180&690", "urank": 4, "mbrank": 2, "verified": false, "verified_type": -1, "verified_reason": ""}, "weibo": [{"user_id": 6264137579, "screen_name": "Coldnessinmyheart2", "id": 5105221066294891, "bid": "P2bP4qpAv", "text": "他总是来求我 却闭口不谈给我什么 其实有句话说的觉得没错 他不给 你还留 就是默认可以不给 我也是故意用的高开低走这一套 当他形成习惯 占了便宜再抽离 男人强大的占有欲控制欲会让他生不如死 我现在看着他每天这么痛苦 和他兄弟乱搞 感觉特别爽 ", "article_url": "", "pics": "", "video_url": "", "location": "", "created_at": "2024-11-27T07:16:55", "source": "iPhone客户端", "attitudes_count": 21, "comments_count": 2, "reposts_count": 0, "topics": "", "at_users": "", "full_created_at": "2024-11-27 07:16:55"}, {"user_id": 6264137579, "screen_name": "Coldnessinmyheart2", "id": 5103746130378919, "bid": "P1zs91AzB", "text": "我曾经说过和他们在一起让我见到了男人人性中最丑恶的一面 其实口风和第一感觉绝对是对的\n但是是我选择的 我总想搏个大的 于是被做局纠缠住 脱不了身 某些角度来说 也是因为我曾经物欲太重摧毁别人的因果 也算是报应 \n买单离场吧 还有真的不能找玩东西的人 会催化很多恶性的事 ", "article_url": "", "pics": "", "video_url": "", "location": "", "created_at": "2024-11-23T05:36:03", "source": "iPhone客户端", "attitudes_count": 9, "comments_count": 2, "reposts_count": 0, "topics": "", "at_users": "", "full_created_at": "2024-11-23 05:36:03"}, {"user_id": 6264137579, "screen_name": "Coldnessinmyheart2", "id": 5103744979042497, "bid": "P1zqhBWmJ", "text": "转发微博", "article_url": "", "pics": "", "video_url": "", "location": "", "created_at": "2024-11-23T05:31:29", "source": "iPhone客户端", "attitudes_count": 13, "comments_count": 0, "reposts_count": 2, "topics": "", "at_users": "", "retweet": {"user_id": 5539845983, "screen_name": "别想拯救我了", "id": 5021668650780350, "bid": "O95Hr3h0i", "text": "别抱怨任何人给你带来的伤害，一切错误都是自身判断力和能力不够造成的 ", "article_url": "", "pics": "", "video_url": "", "location": "", "created_at": "2024-04-10T17:49:27", "source": "iPhone客户端", "attitudes_count": 23, "comments_count": 1, "reposts_count": 10, "topics": "", "at_users": "", "full_created_at": "2024-04-10 17:49:27"}, "full_created_at": "2024-11-23 05:31:29"}, {"user_id": 6264137579, "screen_name": "Coldnessinmyheart2", "id": 5103741533421932, "bid": "P1zkJemcs", "text": "因为看了我手机 第一次被他动手打了 他把刀拿在旁边 叫他停手也不停 打完我爬起来就走了 脑袋嗡嗡的 路上拉黑了他所有联系方式 居然也没哭他一直加我说给我转钱 转头拉黑了 睡了几小时遮住淤青打扮精致 还去酒局应酬 强行笑靥如花 和大哥说着讨巧的话大口灌着酒 想着都是下月的生活费 \n其实如果自己打不倒自己 那就没人打的倒你", "article_url": "", "pics": "", "video_url": "", "location": "", "created_at": "2024-11-23T05:17:47", "source": "iPhone客户端", "attitudes_count": 25, "comments_count": 11, "reposts_count": 0, "topics": "", "at_users": "", "full_created_at": "2024-11-23 05:17:47"}, {"user_id": 6264137579, "screen_name": "Coldnessinmyheart2", "id": 5103349533507805, "bid": "P1p8teIxv", "text": "身上真的有太多人的影子 早已不是我自己了 ", "article_url": "", "pics": "", "video_url": "", "location": "", "created_at": "2024-11-22T03:20:07", "source": "iPhone客户端", "attitudes_count": 19, "comments_count": 2, "reposts_count": 1, "topics": "", "at_users": "", "full_created_at": "2024-11-22 03:20:07"}]}