{"user": {"id": "2516709791", "screen_name": "拉拉爱吃辣_", "gender": "f", "birthday": "", "location": "", "education": "", "company": "", "registration_time": "", "sunshine": "", "statuses_count": 2184, "followers_count": 27000, "follow_count": 900, "description": "干敏皮 粉底一般最白 喜欢自然清透妆感", "profile_url": "https://m.weibo.cn/u/2516709791?", "profile_image_url": "https://tvax4.sinaimg.cn/crop.0.0.512.512.180/9601f19fly8hce6shif2nj20e80e8ab7.jpg?KID=imgbed,tva&Expires=1732888285&ssig=xGTHEApKaW", "avatar_hd": "https://wx4.sinaimg.cn/orj480/9601f19fly8hce6shif2nj20e80e8ab7.jpg", "urank": 27, "mbrank": 6, "verified": true, "verified_type": 0, "verified_reason": "微博原创视频博主"}, "weibo": [{"user_id": 2516709791, "screen_name": "拉拉爱吃辣_", "id": 5105758683794177, "bid": "P2pOcfV2p", "text": "这两天天气太干了 上火上的直接眼睛都肿了\n ", "article_url": "", "pics": "", "video_url": "", "location": "", "created_at": "2024-11-28T18:53:13", "source": "iPhone 15 Pro Max", "attitudes_count": 10, "comments_count": 8, "reposts_count": 0, "topics": "", "at_users": "", "full_created_at": "2024-11-28 18:53:13"}, {"user_id": 2516709791, "screen_name": "拉拉爱吃辣_", "id": 5105378600422838, "bid": "P2fVa1LZY", "text": "随手的一张图 再翻相册看到的时候依旧很美 ", "article_url": "", "pics": "https://wx4.sinaimg.cn/large/9601f19fly1hw0xqc9sbvj22bc334npd.jpg", "video_url": "", "location": "", "created_at": "2024-11-27T17:42:54", "source": "iPhone 15 Pro Max", "attitudes_count": 16, "comments_count": 6, "reposts_count": 1, "topics": "", "at_users": "", "full_created_at": "2024-11-27 17:42:54"}, {"user_id": 2516709791, "screen_name": "拉拉爱吃辣_", "id": 5102800109830548, "bid": "P1aQiFfne", "text": "东京的酒店价格真的是贵的离谱 就这么说吧1500左右的就是相当于我们的全季，有的我觉得还不如\n然后也就21-23左右的大小，总之我门还没出就已经花了我4天在济州岛所有的花销了\n ", "article_url": "", "pics": "", "video_url": "", "location": "", "created_at": "2024-11-20T14:56:53", "source": "iPhone 15 Pro Max", "attitudes_count": 16, "comments_count": 9, "reposts_count": 0, "topics": "", "at_users": "", "full_created_at": "2024-11-20 14:56:53"}]}